screenlogicpy/__init__.py
screenlogicpy/__main__.py
screenlogicpy/cli.py
screenlogicpy/client.py
screenlogicpy/data.py
screenlogicpy/discovery.py
screenlogicpy/gateway.py
screenlogicpy/validation.py
screenlogicpy/const/__init__.py
screenlogicpy/const/common.py
screenlogicpy/const/data.py
screenlogicpy/const/msg.py
screenlogicpy/device_const/__init__.py
screenlogicpy/device_const/chemistry.py
screenlogicpy/device_const/circuit.py
screenlogicpy/device_const/heat.py
screenlogicpy/device_const/pump.py
screenlogicpy/device_const/scg.py
screenlogicpy/device_const/system.py
screenlogicpy/requests/__init__.py
screenlogicpy/requests/button.py
screenlogicpy/requests/chemistry.py
screenlogicpy/requests/client.py
screenlogicpy/requests/config.py
screenlogicpy/requests/datetime.py
screenlogicpy/requests/equipment.py
screenlogicpy/requests/gateway.py
screenlogicpy/requests/heat.py
screenlogicpy/requests/lights.py
screenlogicpy/requests/login.py
screenlogicpy/requests/ping.py
screenlogicpy/requests/protocol.py
screenlogicpy/requests/pump.py
screenlogicpy/requests/request.py
screenlogicpy/requests/scg.py
screenlogicpy/requests/status.py
screenlogicpy/requests/utility.py
screenlogicpy-0.10.2.dist-info/licenses/LICENSE
screenlogicpy-0.10.2.dist-info/METADATA
screenlogicpy-0.10.2.dist-info/WHEEL
screenlogicpy-0.10.2.dist-info/entry_points.txt
screenlogicpy-0.10.2.dist-info/top_level.txt
screenlogicpy-0.10.2.dist-info/RECORD
