Metadata-Version: 2.4
Name: screenlogicpy
Version: 0.10.2
Summary: Interface for Pentair ScreenLogic connected pool controllers over IP via Python
Author-email: Kevin Worrel <kevinworrel@yahoo.com>
License-Expression: GPL-3.0-only
Project-URL: github, https://github.com/dieselrabbit/screenlogicpy
Classifier: Programming Language :: Python :: 3.10
Classifier: Programming Language :: Python :: 3.11
Classifier: Operating System :: OS Independent
Classifier: Development Status :: 3 - Alpha
Requires-Python: >=3.10
License-File: LICENSE
Requires-Dist: async_timeout>=3.0.0
Dynamic: license-file
